{
  "_fv": 47,
  "_type": "recipe",
  "definition": {
    "recipeType": "Crafting",
    "recipeRetstackSize": 1,
    "group": "",
    "cookingBookCategory": "MISC",
    "xpReward": 0.0,
    "cookingTime": 200,
    "craftingBookCategory": "MISC",
    "recipeShapeless": false,
    "recipeSlots": [
      {
        "value": "TAG:forge:stick"
      },
      {
        "value": "TAG:forge:stick"
      },
      {
        "value": "TAG:forge:stick"
      },
      {
        "value": "TAG:forge:stick"
      },
      {
        "value": "Items.LEATHER"
      },
      {
        "value": "TAG:forge:stick"
      },
      {
        "value": "TAG:forge:stick"
      },
      {
        "value": "TAG:forge:stick"
      },
      {
        "value": "TAG:forge:stick"
      }
    ],
    "recipeReturnStack": {
      "value": "Items.ITEM_FRAME"
    },
    "name": "item_frame",
    "namespace": "minecraft"
  }
}